protonox_kivy_core/__init__.py
protonox_kivy_core/hotreload.py
protonox_kivy_core/router_contract.py
protonox_kivy_core/studio_bridge.py
protonox_studio/__init__.py
protonox_studio/flags.py
protonox_studio/cli/__init__.py
protonox_studio/cli/protonox.py
protonox_studio/core/__init__.py
protonox_studio/core/ai.py
protonox_studio/core/asset_injector.py
protonox_studio/core/bluntmine.py
protonox_studio/core/doctor.py
protonox_studio/core/doctor_kivy.py
protonox_studio/core/drop.py
protonox_studio/core/engine.py
protonox_studio/core/injector.py
protonox_studio/core/kivy_introspection.py
protonox_studio/core/layout.py
protonox_studio/core/lifecycle.py
protonox_studio/core/live_reload.py
protonox_studio/core/local_dev_server.py
protonox_studio/core/models.py
protonox_studio/core/place_mode.py
protonox_studio/core/project_context.py
protonox_studio/core/runtime_introspection.py
protonox_studio/core/screen_map.py
protonox_studio/core/server.py
protonox_studio/core/ui_model.py
protonox_studio/core/visual.py
protonox_studio/core/web_to_kivy.py
protonox_studio/core/wireless_client.py
protonox_studio/core/website/protonox-studio/logs/local_dev_server.log
protonox_studio/core/website/protonox-studio/tmp/local_dev_server.pid
protonox_studio/devtools/__init__.py
protonox_studio/devtools/clock_guard.py
protonox_studio/devtools/error_overlay.py
protonox_studio/devtools/kv_strict.py
protonox_studio/devtools/logger.py
protonox_studio/intelligence/__init__.py
protonox_studio/intelligence/beauty_scorer.py
protonox_studio/intelligence/grid_engine.py
protonox_studio/intelligence/spacing_analyzer.py
protonox_studio/intelligence/token_detector.py
protonox_studio/layout/__init__.py
protonox_studio/modules/README.md
protonox_studio/modules/__init__.py
protonox_studio/modules/mercadopago.py
protonox_studio/modules/browser-extension/background.js
protonox_studio/modules/browser-extension/content.js
protonox_studio/modules/browser-extension/manifest.json
protonox_studio-0.1.5.dist-info/licenses/LICENSE
protonox_studio-0.1.5.dist-info/METADATA
protonox_studio-0.1.5.dist-info/WHEEL
protonox_studio-0.1.5.dist-info/entry_points.txt
protonox_studio-0.1.5.dist-info/top_level.txt
protonox_studio-0.1.5.dist-info/RECORD
