Metadata-Version: 2.4
Name: protonox-studio
Version: 0.1.5
Summary: Protonox Studio – motor de diseño inteligente con auditorías y ARC Mode
Author-email: Protonox <protonox@outlook.es>
License-Expression: LicenseRef-Proprietary
Keywords: design,audit,figma,ux,protonox
Classifier: Programming Language :: Python :: 3
Classifier: Operating System :: OS Independent
Requires-Python: >=3.10
License-File: LICENSE
Requires-Dist: watchdog>=4.0.0
Requires-Dist: pyyaml>=6.0
Requires-Dist: requests>=2.31.0
Provides-Extra: web
Requires-Dist: fastapi>=0.95.0; extra == "web"
Requires-Dist: uvicorn>=0.22.0; extra == "web"
Provides-Extra: image
Requires-Dist: pillow>=10.0.0; extra == "image"
Dynamic: license-file
